package/__init__.py
package/package.py
tests/__init__.py
tests/tests_helper.py
tests/helpers/__init__.py
tests/helpers/my_helper.py
tests/unit/__init__.py
tests/unit/test_package.py
python_package_boilerplate-0.1.1.dist-info/LICENSE
python_package_boilerplate-0.1.1.dist-info/METADATA
python_package_boilerplate-0.1.1.dist-info/WHEEL
python_package_boilerplate-0.1.1.dist-info/top_level.txt
python_package_boilerplate-0.1.1.dist-info/RECORD
