Metadata-Version: 2.1
Name: python-package-boilerplate
Version: 0.1.1
Summary: A boilerplate Python package for easy project setup
Home-page: https://github.com/RUNNERS-IM/python-package-boilerplate
Author: Runners Co., Ltd.
Author-email: dev@runners.im
License: UNKNOWN
Platform: UNKNOWN
Classifier: Programming Language :: Python :: 3
Classifier: License :: OSI Approved :: MIT License
Classifier: Operating System :: OS Independent
Classifier: Development Status :: 3 - Alpha
Classifier: Intended Audience :: Developers
Classifier: Topic :: Software Development :: Libraries :: Python Modules
Requires-Python: >=3.6
Requires-Dist: requests
